{
    "users": [
      {
        "id": 1,
        "name": "Hilal Şimşek",
        "age": 25,
        "location": "Antalya",
        "interests": ["Yapay Zeka", "Veri Bilimi", "Teknoloji"]
      },
      {
        "id": 2,
        "name": "Ahmet Yılmaz",
        "age": 30,
        "location": "İstanbul",
        "interests": ["Müzik", "Sinema", "Seyahat"]
      },
      {
        "id": 3,
        "name": "Elif Kaya",
        "age": 22,
        "location": "Ankara",
        "interests": ["Tasarım", "Teknoloji", "Spor"]
      }
    ]
  }